remip/__init__.py
remip/_version.py
remip/main.py
remip/models.py
remip/services.py
remip/solvers/scip_wrapper.py
remip-0.3.3.dist-info/METADATA
remip-0.3.3.dist-info/WHEEL
remip-0.3.3.dist-info/entry_points.txt
remip-0.3.3.dist-info/RECORD
