Metadata-Version: 2.4
Name: remip
Version: 0.3.3
Summary: Add your description here
Author-email: ohtaman <ohtamans@gmail.com>
Requires-Python: >=3.11
Requires-Dist: fastapi
Requires-Dist: pydantic
Requires-Dist: pyscipopt
Requires-Dist: uvicorn
